bitneural32/__init__.py
bitneural32/compiler.py
bitneural32/layers.py
bitneural32/op_codes.py
bitneural32/qat.py
bitneural32/quantize.py
bitneural32-0.0.9.dist-info/licenses/LICENSE
bitneural32-0.0.9.dist-info/METADATA
bitneural32-0.0.9.dist-info/WHEEL
bitneural32-0.0.9.dist-info/top_level.txt
bitneural32-0.0.9.dist-info/RECORD
