Metadata-Version: 2.4
Name: bitneural32
Version: 0.0.9
Summary: BitNeural32: 1.58-bit Ternary Neural Network Compiler & QAT Library for ESP32
Author-email: Aizhee <aizharjamilano@gmail.com>
Maintainer-email: Aizhee <aizharjamilano@gmail.com>
License: MIT
Project-URL: Homepage, https://github.com/Aizhee/python-bitneural32
Project-URL: Repository, https://github.com/Aizhee/python-bitneural32.git
Project-URL: Documentation, https://github.com/Aizhee/python-bitneural32/wiki
Keywords: ternary,neural-network,ESP32,bitnet,quantization,embedded-ml,qat
Classifier: Development Status :: 4 - Beta
Classifier: Intended Audience :: Developers
Classifier: Intended Audience :: Science/Research
Classifier: Topic :: Scientific/Engineering :: Artificial Intelligence
Classifier: Topic :: Software Development :: Embedded Systems
Classifier: License :: OSI Approved :: MIT License
Classifier: Programming Language :: Python :: 3
Classifier: Programming Language :: Python :: 3.9
Classifier: Programming Language :: Python :: 3.10
Classifier: Programming Language :: Python :: 3.11
Classifier: Programming Language :: Python :: 3.12
Classifier: Operating System :: OS Independent
Requires-Python: >=3.9
License-File: LICENSE
Requires-Dist: keras>=3.0.0
Requires-Dist: tensorflow>=2.16.0
Requires-Dist: numpy>=1.21.0
Provides-Extra: dev
Requires-Dist: pytest>=7.0; extra == "dev"
Requires-Dist: pytest-cov>=4.0; extra == "dev"
Requires-Dist: black>=23.0; extra == "dev"
Requires-Dist: flake8>=6.0; extra == "dev"
Requires-Dist: mypy>=1.0; extra == "dev"
Provides-Extra: docs
Requires-Dist: sphinx>=5.0; extra == "docs"
Requires-Dist: sphinx-rtd-theme>=1.2; extra == "docs"
Dynamic: license-file
